LICENSE.txt
MANIFEST.in
README.md
setup.cfg
setup.py
nfer_secure_sandbox_cli/__init__.py
nfer_secure_sandbox_cli/cpscli.sh
nfer_secure_sandbox_cli/nfer-sandbox-cli
nfer_secure_sandbox_cli/scli.sh
nfer_secure_sandbox_cli.egg-info/PKG-INFO
nfer_secure_sandbox_cli.egg-info/SOURCES.txt
nfer_secure_sandbox_cli.egg-info/dependency_links.txt
nfer_secure_sandbox_cli.egg-info/requires.txt
nfer_secure_sandbox_cli.egg-info/top_level.txt
nfer_secure_sandbox_cli/actions/__init__.py
nfer_secure_sandbox_cli/actions/configure.py
nfer_secure_sandbox_cli/actions/destroy.py
nfer_secure_sandbox_cli/actions/initialize.py
nfer_secure_sandbox_cli/actions/launch.py
nfer_secure_sandbox_cli/actions/run.py
nfer_secure_sandbox_cli/actions/setup-old.py
nfer_secure_sandbox_cli/actions/setup.py
nfer_secure_sandbox_cli/scripts/setup.linux.sh
nfer_secure_sandbox_cli/utils/__init__.py
nfer_secure_sandbox_cli/utils/authentication/__init__.py
nfer_secure_sandbox_cli/utils/authentication/authenticate.py
nfer_secure_sandbox_cli/utils/display/__init__.py
nfer_secure_sandbox_cli/utils/display/artefacts_utils.py
nfer_secure_sandbox_cli/utils/display/setup_configs.py
nfer_secure_sandbox_cli/utils/logging/__init__.py
nfer_secure_sandbox_cli/utils/logging/logger.py
nfer_secure_sandbox_cli/utils/logging/verbosity.py
nfer_secure_sandbox_cli/utils/parsing/__init__.py
nfer_secure_sandbox_cli/utils/parsing/yaml.py
nfer_secure_sandbox_cli/utils/sensoriant/__init__.py
nfer_secure_sandbox_cli/utils/sensoriant/algo/__init__.py
nfer_secure_sandbox_cli/utils/sensoriant/algo/algo_utils.py
nfer_secure_sandbox_cli/utils/sensoriant/configuration/__init__.py
nfer_secure_sandbox_cli/utils/sensoriant/configuration/conf.py
nfer_secure_sandbox_cli/utils/sensoriant/execution/__init__.py
nfer_secure_sandbox_cli/utils/sensoriant/execution/exec_utils.py
nfer_secure_sandbox_cli/utils/sensoriant/output/__init__.py
nfer_secure_sandbox_cli/utils/sensoriant/output/output_utils.py
nfer_secure_sandbox_cli/utils/sensoriant/policy/__init__.py
nfer_secure_sandbox_cli/utils/sensoriant/policy/policy_utils.py
nfer_secure_sandbox_cli/utils/sensoriant/projection/__init__.py
nfer_secure_sandbox_cli/utils/sensoriant/projection/data_projection.py
