Metadata-Version: 2.1
Name: nfer-secure-sandbox-cli
Version: 0.2.8.dev0
Summary: Nfer Secure Sandbox CLI - helps client run algorithm securely over sandboxes
Home-page: https://github.com/lumenbiomics/nfer-secure-sandbox-cli
Author: sumitkhanna@nference.net
Author-email: sumitkhanna@nference.net
License: MIT
Download-URL: https://github.com/lumenbiomics/nfer-secure-sandbox-cli/archive/v0.2.8-dev.tar.gz
Keywords: Nference,Sandbox,Confidential-Computing
Platform: UNKNOWN
Classifier: Development Status :: 3 - Alpha
Classifier: Topic :: Software Development :: Build Tools
Classifier: License :: OSI Approved :: MIT License
Classifier: Programming Language :: Python :: 3.4
Classifier: Programming Language :: Python :: 3.5
Classifier: Programming Language :: Python :: 3.6
Classifier: Programming Language :: Python :: 3.7
Classifier: Programming Language :: Python :: 3.8
Classifier: Programming Language :: Python :: 3.9
